swh/__init__.py
swh/loader/__init__.py
swh/loader/debian/__init__.py
swh/loader/debian/converters.py
swh/loader/debian/loader.py
swh/loader/debian/tasks.py
swh/loader/debian/tests/__init__.py
swh/loader/debian/tests/test_loader.py
swh.loader.debian-0.0.13.dist-info/AUTHORS
swh.loader.debian-0.0.13.dist-info/LICENSE
swh.loader.debian-0.0.13.dist-info/METADATA
swh.loader.debian-0.0.13.dist-info/WHEEL
swh.loader.debian-0.0.13.dist-info/top_level.txt
swh.loader.debian-0.0.13.dist-info/RECORD
