Metadata-Version: 2.1
Name: swh.loader.debian
Version: 0.0.13
Summary: Software Heritage Debian loader
Home-page: https://forge.softwareheritage.org/diffusion/DLDDEB/
Author: Software Heritage developers
Author-email: swh-devel@inria.fr
License: UNKNOWN
Project-URL: Funding, https://www.softwareheritage.org/donate
Project-URL: Source, https://forge.softwareheritage.org/source/swh-loader-debian
Project-URL: Bug Reports, https://forge.softwareheritage.org/maniphest
Platform: UNKNOWN
Classifier: Programming Language :: Python :: 3
Classifier: Intended Audience :: Developers
Classifier: License :: OSI Approved :: GNU General Public License v3 (GPLv3)
Classifier: Operating System :: OS Independent
Classifier: Development Status :: 5 - Production/Stable
Requires-Dist: python-debian
Requires-Dist: vcversioner
Requires-Dist: swh.core
Requires-Dist: swh.loader.core (>=0.0.37)
Requires-Dist: swh.model (>=0.0.27)
Requires-Dist: swh.scheduler (>=0.0.39)
Requires-Dist: swh.storage[schemata]
Provides-Extra: testing
Requires-Dist: pytest ; extra == 'testing'
Requires-Dist: requests-mock ; extra == 'testing'
Requires-Dist: sqlalchemy ; extra == 'testing'
